[
    {
        "nombre": "Video 1",
        "descripcion": "de que se trata",
        "url": "link.video"
    },
    {
        "nombre": "Video 1",
        "descripcion": "de que se trata",
        "url": "link.video"
    },
    {
        "nombre": "Video 1",
        "descripcion": "de que se trata",
        "url": "link.video"
    },
    {
        "nombre": "Video 1",
        "descripcion": "de que se trata",
        "url": "link.video"
    },
    {
        "nombre": "Video 1",
        "descripcion": "de que se trata",
        "url": "link.video"
    }
]